Friends_RISC-V/regfile.v
module regfile(input         clk,
               input         reg_write,
               input  [4:0]  read_register1, read_register2, write_register,
               input  [63:0] write_data,
               output [63:0] read_data1, read_data2);
  reg[63:0] register[31:0];

  always @(posedge clk)
    if (reg_write) register[write_register] <= write_data;

  assign read_data1 = (read_register1 != 0) ? register[read_register1]: 0;
  assign read_data2 = (read_register2 != 0) ? register[read_register2]: 0;

endmodule

Friends_RISC-V/regfile_test.v
`include "regfile.v"

module testbench();

  reg clk;
  reg reg_write;

  reg [4:0]   read_register1, read_register2, write_register;
  reg [63:0]  write_data;
  wire [63:0] read_data1, read_data2;

  regfile testreg(clk, reg_write, read_register1, read_register2, write_register, write_data, read_data1, read_data2);

  initial
    begin
      $dumpfile("regfile_test.vcd");
      $dumpvars(0, testreg);

      $monitor("%h, %h, %h, %h", testreg.register[1], testreg.register[2],
               testreg.read_data1, testreg.read_data2);

      $display("register[1] register[2] read_data1  read_data2");

      read_register1<=1; read_register2<=2;write_register<=1; write_data<=5;

      reg_write <= 1; #10;
      reg_write <= 0; #10;

      read_register1<=1; read_register2<=2; write_register<=2; write_data<=6;

      reg_write <= 1; #10;
      reg_write <= 0; #10;

      read_register1<=1; read_register2<=2; write_register<=1; write_data<=8;

      reg_write <= 1; #10;
      reg_write <= 0; #10;

      // 0 register
      read_register1<=0; read_register2<=2; write_register<=0; write_data<=8;

      reg_write <= 1; #10;
      reg_write <= 0; #10;
      
      #200;
      $finish;
    end

  // generate clock
  always
    begin
      clk <= 1; #5; clk <= 0; #5;
    end

endmodule

Friends_RISC-V/regfile_test.vcd
$date
	Tue Aug 27 21:22:04 2019
$end
$version
	Icarus Verilog
$end
$timescale
	1s
$end
$scope module testbench $end
$scope module testreg $end
$var wire 1 ! clk $end
$var wire 5 " read_register1 [4:0] $end
$var wire 5 # read_register2 [4:0] $end
$var wire 1 $ reg_write $end
$var wire 64 % write_data [63:0] $end
$var wire 5 & write_register [4:0] $end
$var wire 64 ' read_data2 [63:0] $end
$var wire 64 ( read_data1 [63:0] $end
$upscope $end
$upscope $end
$enddefinitions $end
#0
$dumpvars
b101 (
bx '
b1 &
b101 %
1$
b10 #
b1 "
1!
$end
#5
0!
#10
1!
0$
#15
0!
#20
b110 '
1!
1$
b110 %
b10 &
#25
0!
#30
1!
0$
#35
0!
#40
b1000 (
1!
1$
b1000 %
b1 &
#45
0!
#50
1!
0$
#55
0!
#60
b0 (
1!
1$
b0 &
b0 "
#65
0!
#70
1!
0$
